[{"repo_name": "spring-boot", "repo_url": "spring-projects/spring-boot", "issue_html_url": "https://github.com/spring-projects/spring-boot/issues/27254", "earliest_issue_date": "2021-07-12T05:53:51Z", "fix_commit_hash": "a4709f0979f6150b6a4584b7a319fdd8d067404b", "tipo": "Commit", "commit_author": "Stephane Nicoll", "commiter": "Stephane Nicoll", "commit_date": "2021-07-12T07:53:51+02:00", "committer_data": "2021-07-12T07:55:28+02:00", "changed_files": 1, "deletions": 1, "insertions": 1, "lines": 2, "dmm_unit_size": null, "dmm_unit_complexity": null, "dmm_unit_interfacing": null, "files_exts": ["gradle"], "inducing_commit_hash_pyszz": [], "inducing_commit_hash_pd": []}, {"repo_name": "spring-boot", "repo_url": "spring-projects/spring-boot", "issue_html_url": "https://github.com/spring-projects/spring-boot/issues/27252", "earliest_issue_date": "2021-07-12T05:53:49Z", "fix_commit_hash": "580e01283aba3cfb10fbc7d0b8ca79ce9d98ad4a", "tipo": "Commit", "commit_author": "Stephane Nicoll", "commiter": "Stephane Nicoll", "commit_date": "2021-07-12T07:53:49+02:00", "committer_data": "2021-07-12T07:55:27+02:00", "changed_files": 1, "deletions": 1, "insertions": 1, "lines": 2, "dmm_unit_size": null, "dmm_unit_complexity": null, "dmm_unit_interfacing": null, "files_exts": ["gradle"], "inducing_commit_hash_pyszz": [], "inducing_commit_hash_pd": []}, {"repo_name": "spring-boot", "repo_url": "spring-projects/spring-boot", "issue_html_url": "https://github.com/spring-projects/spring-boot/issues/27250", "earliest_issue_date": "2021-07-12T05:53:47Z", "fix_commit_hash": "49134f870ec06b5e5540003c71ba147a8d09609d", "tipo": "Commit", "commit_author": "Stephane Nicoll", "commiter": "Stephane Nicoll", "commit_date": "2021-07-12T07:53:47+02:00", "committer_data": "2021-07-12T07:55:27+02:00", "changed_files": 1, "deletions": 1, "insertions": 1, "lines": 2, "dmm_unit_size": null, "dmm_unit_complexity": null, "dmm_unit_interfacing": null, "files_exts": ["gradle"], "inducing_commit_hash_pyszz": [], "inducing_commit_hash_pd": []}, {"repo_name": "spring-boot", "repo_url": "spring-projects/spring-boot", "issue_html_url": "https://github.com/spring-projects/spring-boot/issues/27245", "earliest_issue_date": "2021-07-11T06:12:09Z", "fix_commit_hash": "afb96af0ebeda594e7c46fdfdf950399f5037631", "tipo": "Commit", "commit_author": "Stephane Nicoll", "commiter": "Stephane Nicoll", "commit_date": "2021-07-11T08:12:09+02:00", "committer_data": "2021-07-11T08:12:09+02:00", "changed_files": 1, "deletions": 1, "insertions": 1, "lines": 2, "dmm_unit_size": null, "dmm_unit_complexity": null, "dmm_unit_interfacing": null, "files_exts": ["properties"], "inducing_commit_hash_pyszz": [], "inducing_commit_hash_pd": []}, {"repo_name": "spring-boot", "repo_url": "spring-projects/spring-boot", "issue_html_url": "https://github.com/spring-projects/spring-boot/issues/27243", "earliest_issue_date": "2021-07-11T06:12:07Z", "fix_commit_hash": "bed528f2031ca120b1a050aaba8b55ceeca2ddc2", "tipo": "Commit", "commit_author": "Stephane Nicoll", "commiter": "Stephane Nicoll", "commit_date": "2021-07-11T08:12:07+02:00", "committer_data": "2021-07-11T08:12:07+02:00", "changed_files": 1, "deletions": 1, "insertions": 1, "lines": 2, "dmm_unit_size": null, "dmm_unit_complexity": null, "dmm_unit_interfacing": null, "files_exts": ["gradle"], "inducing_commit_hash_pyszz": [], "inducing_commit_hash_pd": []}, {"repo_name": "spring-boot", "repo_url": "spring-projects/spring-boot", "issue_html_url": "https://github.com/spring-projects/spring-boot/issues/27241", "earliest_issue_date": "2021-07-11T06:12:05Z", "fix_commit_hash": "3c6db2bc2817f10253d9fc0ca6cce36ba7592d85", "tipo": "Commit", "commit_author": "Stephane Nicoll", "commiter": "Stephane Nicoll", "commit_date": "2021-07-11T08:12:06+02:00", "committer_data": "2021-07-11T08:12:06+02:00", "changed_files": 1, "deletions": 1, "insertions": 1, "lines": 2, "dmm_unit_size": null, "dmm_unit_complexity": null, "dmm_unit_interfacing": null, "files_exts": ["gradle"], "inducing_commit_hash_pyszz": [], "inducing_commit_hash_pd": []}, {"repo_name": "spring-boot", "repo_url": "spring-projects/spring-boot", "issue_html_url": "https://github.com/spring-projects/spring-boot/issues/27239", "earliest_issue_date": "2021-07-11T06:12:03Z", "fix_commit_hash": "88e0916ad64319c888ffe61226e21ff1d83d300c", "tipo": "Commit", "commit_author": "Stephane Nicoll", "commiter": "Stephane Nicoll", "commit_date": "2021-07-11T08:12:04+02:00", "committer_data": "2021-07-11T08:12:04+02:00", "changed_files": 1, "deletions": 1, "insertions": 1, "lines": 2, "dmm_unit_size": null, "dmm_unit_complexity": null, "dmm_unit_interfacing": null, "files_exts": ["gradle"], "inducing_commit_hash_pyszz": [], "inducing_commit_hash_pd": []}, {"repo_name": "spring-boot", "repo_url": "spring-projects/spring-boot", "issue_html_url": "https://github.com/spring-projects/spring-boot/issues/27236", "earliest_issue_date": "2021-07-10T15:38:46Z", "fix_commit_hash": "d67089cdfe0a706ecef7c66d9d249269b21fcaf5", "tipo": "Commit", "commit_author": "Stephane Nicoll", "commiter": "Stephane Nicoll", "commit_date": "2021-07-10T17:38:44+02:00", "committer_data": "2021-07-10T17:38:44+02:00", "changed_files": 1, "deletions": 10, "insertions": 20, "lines": 30, "dmm_unit_size": null, "dmm_unit_complexity": null, "dmm_unit_interfacing": null, "files_exts": ["java"], "inducing_commit_hash_pyszz": [], "inducing_commit_hash_pd": []}, {"repo_name": "spring-boot", "repo_url": "spring-projects/spring-boot", "issue_html_url": "https://github.com/spring-projects/spring-boot/issues/27234", "earliest_issue_date": "2021-07-10T11:05:44Z", "fix_commit_hash": "a7334deb5466c7774718c8195194a97d57bbaea1", "tipo": "Commit", "commit_author": "Andy Wilkinson", "commiter": "Andy Wilkinson", "commit_date": "2021-07-10T12:05:40+01:00", "committer_data": "2021-07-10T12:05:40+01:00", "changed_files": 1, "deletions": 2, "insertions": 16, "lines": 18, "dmm_unit_size": null, "dmm_unit_complexity": null, "dmm_unit_interfacing": null, "files_exts": ["xml"], "inducing_commit_hash_pyszz": [], "inducing_commit_hash_pd": []}, {"repo_name": "spring-boot", "repo_url": "spring-projects/spring-boot", "issue_html_url": "https://github.com/spring-projects/spring-boot/issues/27232", "earliest_issue_date": "2021-07-10T09:18:14Z", "fix_commit_hash": "79990a1b9c8c4b4fa865f1234cfbc071dc4a0646", "tipo": "Commit", "commit_author": "Andy Wilkinson", "commiter": "Andy Wilkinson", "commit_date": "2021-07-22T08:26:36+01:00", "committer_data": "2021-07-22T08:26:36+01:00", "changed_files": 1, "deletions": 1, "insertions": 1, "lines": 2, "dmm_unit_size": null, "dmm_unit_complexity": null, "dmm_unit_interfacing": null, "files_exts": ["yml"], "inducing_commit_hash_pyszz": [], "inducing_commit_hash_pd": []}]