[{"repo_name": "spring-boot", "repo_url": "spring-projects/spring-boot", "issue_html_url": "https://github.com/spring-projects/spring-boot/issues/36662", "earliest_issue_date": "2023-08-01T18:42:24Z", "fix_commit_hash": "28b3054a9eddc71599cd73f652da088ba2155c99", "tipo": "Commit", "commit_author": "Andy Wilkinson", "commiter": "Andy Wilkinson", "commit_date": "2023-08-01T19:58:28+01:00", "committer_data": "2023-08-01T19:58:28+01:00", "changed_files": 1, "deletions": 1, "insertions": 2, "lines": 3, "dmm_unit_size": null, "dmm_unit_complexity": null, "dmm_unit_interfacing": null, "files_exts": ["java"], "inducing_commit_hash_pyszz": []}, {"repo_name": "spring-boot", "repo_url": "spring-projects/spring-boot", "issue_html_url": "https://github.com/spring-projects/spring-boot/issues/36661", "earliest_issue_date": "2023-08-01T17:14:08Z", "fix_commit_hash": "806aa45279c4439dba58cab9a4e924dd546f18df", "tipo": "Commit", "commit_author": "Andy Wilkinson", "commiter": "Andy Wilkinson", "commit_date": "2023-08-01T18:14:03+01:00", "committer_data": "2023-08-01T18:14:03+01:00", "changed_files": 29, "deletions": 11, "insertions": 153, "lines": 164, "dmm_unit_size": null, "dmm_unit_complexity": null, "dmm_unit_interfacing": null, "files_exts": ["java", "java", "java", "imports", "imports", "imports", "imports", "imports", "imports", "imports", "imports", "imports", "imports", "imports", "imports", "imports", "imports", "java", "java", "java", "java", "java", "java", "java", "java", "java", "java", "java", "java"], "inducing_commit_hash_pyszz": []}, {"repo_name": "spring-boot", "repo_url": "spring-projects/spring-boot", "issue_html_url": "https://github.com/spring-projects/spring-boot/issues/36660", "earliest_issue_date": "2023-08-01T14:34:16Z", "fix_commit_hash": "4877e4d1e3a65d1ce23c137b9d26a535cacb1908", "tipo": "Commit", "commit_author": "Moritz Halbritter", "commiter": "Moritz Halbritter", "commit_date": "2024-09-16T10:59:04+02:00", "committer_data": "2024-09-16T11:27:26+02:00", "changed_files": 2, "deletions": 4, "insertions": 45, "lines": 49, "dmm_unit_size": 1.0, "dmm_unit_complexity": 1.0, "dmm_unit_interfacing": 0.5, "files_exts": ["java", "java"], "inducing_commit_hash_pyszz": ["e2262284f1065a664fb52a3fa24a7fce9f01f244"]}, {"repo_name": "spring-boot", "repo_url": "spring-projects/spring-boot", "issue_html_url": "https://github.com/spring-projects/spring-boot/issues/36659", "earliest_issue_date": "2023-08-01T14:10:48Z", "fix_commit_hash": "421448233fcead63366db296e80cf2f9d50dd2bd", "tipo": "Commit", "commit_author": "Stephane Nicoll", "commiter": "Stephane Nicoll", "commit_date": "2023-08-02T12:41:17+02:00", "committer_data": "2023-08-09T11:18:25+02:00", "changed_files": 2, "deletions": 14, "insertions": 1, "lines": 15, "dmm_unit_size": null, "dmm_unit_complexity": null, "dmm_unit_interfacing": null, "files_exts": ["java", "java"], "inducing_commit_hash_pyszz": ["f4985abf3cd299f0842d9f474942c418f177eb13"]}, {"repo_name": "spring-boot", "repo_url": "spring-projects/spring-boot", "issue_html_url": "https://github.com/spring-projects/spring-boot/issues/36654", "earliest_issue_date": "2023-07-31T15:16:20Z", "fix_commit_hash": "922f66a85d3cdd151c137a6a84ec99b04566b618", "tipo": "Commit", "commit_author": "Stephane Nicoll", "commiter": "Stephane Nicoll", "commit_date": "2023-07-31T17:16:17+02:00", "committer_data": "2023-07-31T17:16:17+02:00", "changed_files": 1, "deletions": 2, "insertions": 1, "lines": 3, "dmm_unit_size": null, "dmm_unit_complexity": null, "dmm_unit_interfacing": null, "files_exts": ["java"], "inducing_commit_hash_pyszz": []}, {"repo_name": "spring-boot", "repo_url": "spring-projects/spring-boot", "issue_html_url": "https://github.com/spring-projects/spring-boot/issues/36651", "earliest_issue_date": "2023-07-31T12:27:05Z", "fix_commit_hash": "51008a7d39f36620e87af6f325c6d897e5adbd86", "tipo": "Commit", "commit_author": "Moritz Halbritter", "commiter": "Moritz Halbritter", "commit_date": "2023-08-01T10:32:58+02:00", "committer_data": "2023-08-01T10:32:58+02:00", "changed_files": 11, "deletions": 34, "insertions": 567, "lines": 601, "dmm_unit_size": 1.0, "dmm_unit_complexity": 1.0, "dmm_unit_interfacing": 0.9349593495934959, "files_exts": ["java", "java", "java", "java", "adoc", "java", "java", "java", "java", "java", "java"], "inducing_commit_hash_pyszz": ["54e99d68fabbf6a810789a74abc4af03b25158d3"]}, {"repo_name": "spring-boot", "repo_url": "spring-projects/spring-boot", "issue_html_url": "https://github.com/spring-projects/spring-boot/issues/36637", "earliest_issue_date": "2023-07-28T13:05:51Z", "fix_commit_hash": "32c91af440544effe40516927cc768c3c401a412", "tipo": "Commit", "commit_author": "Moritz Halbritter", "commiter": "Moritz Halbritter", "commit_date": "2023-07-31T09:21:43+02:00", "committer_data": "2023-07-31T11:51:17+02:00", "changed_files": 10, "deletions": 42, "insertions": 741, "lines": 783, "dmm_unit_size": 1.0, "dmm_unit_complexity": 1.0, "dmm_unit_interfacing": 0.8928571428571429, "files_exts": ["java", "java", "java", "adoc", "java", "java", "java", "java", "java", "java"], "inducing_commit_hash_pyszz": ["f33874e98ee6e5026089a4bc9091559744cd5c75"]}, {"repo_name": "spring-boot", "repo_url": "spring-projects/spring-boot", "issue_html_url": "https://github.com/spring-projects/spring-boot/issues/36635", "earliest_issue_date": "2023-07-28T11:22:51Z", "fix_commit_hash": "f3d623bb1d47281024ab57d9d58176fec3cfc643", "tipo": "Commit", "commit_author": "Andy Wilkinson", "commiter": "Andy Wilkinson", "commit_date": "2023-07-28T12:22:48+01:00", "committer_data": "2023-07-28T12:22:48+01:00", "changed_files": 5, "deletions": 20, "insertions": 20, "lines": 40, "dmm_unit_size": null, "dmm_unit_complexity": null, "dmm_unit_interfacing": null, "files_exts": ["java", "java", "java", "java", "java"], "inducing_commit_hash_pyszz": []}, {"repo_name": "spring-boot", "repo_url": "spring-projects/spring-boot", "issue_html_url": "https://github.com/spring-projects/spring-boot/issues/36634", "earliest_issue_date": "2023-07-28T11:22:39Z", "fix_commit_hash": "65bc351847695c95ceb69292631e56993a6939f0", "tipo": "Commit", "commit_author": "Andy Wilkinson", "commiter": "Andy Wilkinson", "commit_date": "2023-07-28T12:22:36+01:00", "committer_data": "2023-07-28T12:22:36+01:00", "changed_files": 5, "deletions": 20, "insertions": 20, "lines": 40, "dmm_unit_size": null, "dmm_unit_complexity": null, "dmm_unit_interfacing": null, "files_exts": ["java", "java", "java", "java", "java"], "inducing_commit_hash_pyszz": []}, {"repo_name": "spring-boot", "repo_url": "spring-projects/spring-boot", "issue_html_url": "https://github.com/spring-projects/spring-boot/issues/36633", "earliest_issue_date": "2023-07-28T11:22:27Z", "fix_commit_hash": "3e99118a486e733e8fda064cfbcfcb6bc953a27f", "tipo": "Commit", "commit_author": "Andy Wilkinson", "commiter": "Andy Wilkinson", "commit_date": "2023-07-28T12:22:21+01:00", "committer_data": "2023-07-28T12:22:21+01:00", "changed_files": 5, "deletions": 20, "insertions": 20, "lines": 40, "dmm_unit_size": null, "dmm_unit_complexity": null, "dmm_unit_interfacing": null, "files_exts": ["java", "java", "java", "java", "java"], "inducing_commit_hash_pyszz": []}]