[
    {
        "fix_commit_hash": "9fa7c84693989da1702a25e43163acab75468d03",
        "repo_name": "graal",
        "best_scenario_issue_date": "2017-12-12T13:07:09-08:00"
    },
    {
        "fix_commit_hash": "866605d71e3cc625c19cf37e097e7a3e5ce6a985",
        "repo_name": "graal",
        "best_scenario_issue_date": "2020-06-25T15:29:37+01:00"
    },
    {
        "fix_commit_hash": "ddd6d139049cea45a299e702a7d69dca10b749d6",
        "repo_name": "graal",
        "best_scenario_issue_date": "2021-03-16T19:01:31+02:00"
    },
    {
        "fix_commit_hash": "1e0d8ea531f25bbc0dfc7a9c8e2005358ff69f41",
        "repo_name": "graal",
        "best_scenario_issue_date": "2019-12-19T10:15:49+01:00"
    },
    {
        "fix_commit_hash": "deffa4fcec937aa570f12ddf1fc0a6d2cc11d683",
        "repo_name": "graal",
        "best_scenario_issue_date": "2019-01-09T11:41:37-08:00"
    },
    {
        "fix_commit_hash": "96fdebee3bc74345ca7fbb9d2f3dd581c5366e05",
        "repo_name": "graal",
        "best_scenario_issue_date": "2021-04-09T16:26:57+02:00"
    },
    {
        "fix_commit_hash": "599358d3bdd4b73180a3dedb57de04e5d1f91964",
        "repo_name": "graal",
        "best_scenario_issue_date": "2018-10-03T18:09:31+02:00"
    },
    {
        "fix_commit_hash": "7b6d5ee4dc5accd2848703ab7285c4b12be666cb",
        "repo_name": "graal",
        "best_scenario_issue_date": "2017-04-14T13:42:39+02:00"
    },
    {
        "fix_commit_hash": "6d777ed865ed29b25a01bb592b27057e998c8baa",
        "repo_name": "graal",
        "best_scenario_issue_date": "2019-03-17T19:17:01+01:00"
    },
    {
        "fix_commit_hash": "75a32e3a6b04ff49e1c84cc83aa6520f2a5dcd66",
        "repo_name": "graal",
        "best_scenario_issue_date": "2021-09-28T10:59:33+02:00"
    }
]